other_access/__init__.py
other_access-0.0.6.dist-info/METADATA
other_access-0.0.6.dist-info/WHEEL
other_access-0.0.6.dist-info/top_level.txt
other_access-0.0.6.dist-info/RECORD
