Metadata-Version: 2.1
Name: other-access
Version: 0.0.6
Summary: os.access() alternative which can check access for other users
Home-page: https://github.com/yaroslaff/other_access
Author: Yaroslav Polyakov
Author-email: yaroslaff@gmail.com
License: none
Platform: UNKNOWN
